loom/README.md
loom/__init__.py
loom/api/README.md
loom/api/__init__.py
loom/api/app.py
loom/api/models.py
loom/api/stream_api.py
loom/config/__init__.py
loom/config/base.py
loom/config/execution.py
loom/config/fractal.py
loom/config/knowledge.py
loom/config/llm.py
loom/config/memory.py
loom/config/tool.py
loom/events/README.md
loom/events/__init__.py
loom/events/actions.py
loom/events/event_bus.py
loom/events/handlers.py
loom/events/memory_transport.py
loom/events/nats_transport.py
loom/events/sse_formatter.py
loom/events/stream_converter.py
loom/events/transport.py
loom/exceptions.py
loom/fractal/README.md
loom/fractal/__init__.py
loom/fractal/allocation.py
loom/fractal/budget.py
loom/fractal/container.py
loom/fractal/memory.py
loom/fractal/resolvers.py
loom/fractal/sync.py
loom/fractal/synthesizer.py
loom/fractal/utils.py
loom/memory/README.md
loom/memory/__init__.py
loom/memory/compression.py
loom/memory/context.py
loom/memory/core.py
loom/memory/fact_extractor.py
loom/memory/factory.py
loom/memory/layers/__init__.py
loom/memory/layers/base.py
loom/memory/layers/circular.py
loom/memory/layers/priority.py
loom/memory/sanitizers.py
loom/memory/task_context.py
loom/memory/tokenizer.py
loom/memory/types.py
loom/memory/vector_store.py
loom/orchestration/README.md
loom/orchestration/__init__.py
loom/orchestration/agent.py
loom/orchestration/agent_workflow.py
loom/orchestration/base.py
loom/orchestration/base_node.py
loom/orchestration/crew.py
loom/orchestration/eventbus_delegation.py
loom/orchestration/meta_tools.py
loom/orchestration/pipeline_builder.py
loom/orchestration/router.py
loom/orchestration/sequential_workflow.py
loom/orchestration/workflow.py
loom/protocol/README.md
loom/protocol/__init__.py
loom/protocol/agent_card.py
loom/protocol/mcp.py
loom/protocol/memory_ops.py
loom/protocol/node.py
loom/protocol/streaming.py
loom/protocol/task.py
loom/providers/README.md
loom/providers/__init__.py
loom/providers/base.py
loom/providers/embedding/__init__.py
loom_agent-0.4.5.dist-info/METADATA
loom_agent-0.4.5.dist-info/WHEEL
loom_agent-0.4.5.dist-info/licenses/LICENSE
loom_agent-0.4.5.dist-info/RECORD
