Metadata-Version: 2.4
Name: loom-agent
Version: 0.4.5
Summary: Enterprise-grade recursive state machine agent framework with event sourcing, multi-agent collaboration, hierarchical memory, and RAG integration
License: Apache-2.0 with Commons Clause
License-File: LICENSE
Keywords: ai,llm,agent,multi-agent,rag,tooling,asyncio
Author: kongusen
Author-email: wanghaishan0210@gmail.com
Requires-Python: >=3.11,<4.0
Classifier: Development Status :: 3 - Alpha
Classifier: Framework :: AsyncIO
Classifier: Intended Audience :: Developers
Classifier: License :: Other/Proprietary License
Classifier: Programming Language :: Python
Classifier: Programming Language :: Python :: 3
Classifier: Programming Language :: Python :: 3.11
Classifier: Programming Language :: Python :: 3.12
Classifier: Programming Language :: Python :: 3.13
Classifier: Programming Language :: Python :: 3.14
Classifier: Topic :: Scientific/Engineering :: Artificial Intelligence
Classifier: Topic :: Software Development :: Libraries
Classifier: Typing :: Typed
Provides-Extra: all
Provides-Extra: anthropic
Provides-Extra: llm
Provides-Extra: nats
Provides-Extra: postgres
Provides-Extra: redis
Provides-Extra: studio
Requires-Dist: asyncpg (>=0.29.0,<0.30.0) ; extra == "postgres"
Requires-Dist: nats-py (>=2.6.0,<3.0.0) ; extra == "nats" or extra == "all"
Requires-Dist: numpy (>=1.26.0,<2.0.0)
Requires-Dist: pgvector (>=0.2.0,<0.3.0) ; extra == "postgres"
Requires-Dist: pydantic (>=2.5.0,<3.0.0)
Requires-Dist: pyyaml (>=6.0,<7.0)
Requires-Dist: redis (>=5.0.1,<6.0.0) ; extra == "redis" or extra == "all"
Requires-Dist: rich (>=13.7.0)
Requires-Dist: structlog (>=24.1.0,<25.0.0)
Requires-Dist: tiktoken (>=0.12.0,<0.13.0)
Requires-Dist: websockets (>=12.0,<13.0) ; extra == "studio"
Project-URL: Documentation, https://github.com/kongusen/loom-agent#readme
Project-URL: Homepage, https://github.com/kongusen/loom-agent
Project-URL: Repository, https://github.com/kongusen/loom-agent
